setup.py
learning_probability_distributions/Binomialdistribution.py
learning_probability_distributions/Gaussiandistribution.py
learning_probability_distributions/Generaldistribution.py
learning_probability_distributions/__init__.py
learning_probability_distributions.egg-info/PKG-INFO
learning_probability_distributions.egg-info/SOURCES.txt
learning_probability_distributions.egg-info/dependency_links.txt
learning_probability_distributions.egg-info/not-zip-safe
learning_probability_distributions.egg-info/top_level.txt